MANIFEST.in
README.txt
setup.py
Products/__init__.py
Products/__init__.pyc
Products.SimplePortlet.egg-info/PKG-INFO
Products.SimplePortlet.egg-info/SOURCES.txt
Products.SimplePortlet.egg-info/dependency_links.txt
Products.SimplePortlet.egg-info/entry_points.txt
Products.SimplePortlet.egg-info/namespace_packages.txt
Products.SimplePortlet.egg-info/not-zip-safe
Products.SimplePortlet.egg-info/requires.txt
Products.SimplePortlet.egg-info/top_level.txt
Products/SimplePortlet/Permissions.py
Products/SimplePortlet/SimplePortletTool.py
Products/SimplePortlet/__init__.py
Products/SimplePortlet/config.py
Products/SimplePortlet/tool.gif
Products/SimplePortlet/Extensions/Install.py
Products/SimplePortlet/Extensions/__init__.py
Products/SimplePortlet/content/__init__.py
Products/SimplePortlet/content/cmfsinportlet.py
Products/SimplePortlet/content/portlet.py
Products/SimplePortlet/content/topicportlet.py
Products/SimplePortlet/i18n/manual.pot
Products/SimplePortlet/i18n/merge.sh
Products/SimplePortlet/i18n/plone-simpleportlet-cs.po
Products/SimplePortlet/i18n/plone-simpleportlet-da.po
Products/SimplePortlet/i18n/plone-simpleportlet-fi.po
Products/SimplePortlet/i18n/plone-simpleportlet-he.po
Products/SimplePortlet/i18n/plone-simpleportlet.pot
Products/SimplePortlet/i18n/rebuild-pot.sh
Products/SimplePortlet/i18n/simpleportlet-cs.po
Products/SimplePortlet/i18n/simpleportlet-da.po
Products/SimplePortlet/i18n/simpleportlet-fi.po
Products/SimplePortlet/i18n/simpleportlet-he.po
Products/SimplePortlet/i18n/simpleportlet.pot
Products/SimplePortlet/skins/SimplePortlet/configure_portlets.py
Products/SimplePortlet/skins/SimplePortlet/portlet_cmfsin_macros.pt
Products/SimplePortlet/skins/SimplePortlet/portlet_icon.gif
Products/SimplePortlet/skins/SimplePortlet/portlet_setup.pt
Products/SimplePortlet/skins/SimplePortlet/portlet_simpleportlet.pt
Products/SimplePortlet/skins/SimplePortlet/portlet_simpleportlet_macros.pt
Products/SimplePortlet/skins/SimplePortlet/portlet_topicportlet_macros.pt
Products/SimplePortlet/skins/SimplePortlet/portlet_view.pt
Products/SimplePortlet/tests/SimplePortletTC.py
Products/SimplePortlet/tests/__init__.py
Products/SimplePortlet/tests/framework.py
Products/SimplePortlet/tests/testPortletCreation.py
Products/SimplePortlet/tests/testSetup.py
Products/SimplePortlet/tests/testSimplePortletTool.py
docs/HISTORY.txt
docs/INSTALL.txt
