Metadata-Version: 1.0
Name: Products.SimplePortlet
Version: 1.2
Summary: Portlets as content-types
Home-page: http://svn.plone.org/svn/collective/Products.SimplePortlet
Author: Plone Foundation
Author-email: Wouter.VandenHove@UGent.be
License: GPL
Platform: UNKNOWN
Classifier: Framework :: Plone
Classifier: Programming Language :: Python
